MANIFEST.in
README.rst
setup.py
docs/HISTORY.rst
src/trinket/__init__.py
src/trinket/app.py
src/trinket/extensions.py
src/trinket/handler.py
src/trinket/http.py
src/trinket/lifecycle.py
src/trinket/proto.py
src/trinket/request.py
src/trinket/response.py
src/trinket/server.py
src/trinket/testing.py
src/trinket/websockets.py
src/trinket.egg-info/PKG-INFO
src/trinket.egg-info/SOURCES.txt
src/trinket.egg-info/dependency_links.txt
src/trinket.egg-info/entry_points.txt
src/trinket.egg-info/not-zip-safe
src/trinket.egg-info/requires.txt
src/trinket.egg-info/top_level.txt
src/trinket/parsers/__init__.py
src/trinket/parsers/multipart.py
src/trinket/parsers/urlencoded.py
tests/conftest.py
tests/test_body_parsing.py
tests/test_cookies.py
tests/test_errors.py
tests/test_parser.py
tests/test_query.py
tests/test_request.py
tests/test_response.py
tests/test_websockets.py