Metadata-Version: 1.0
Name: trinket
Version: 0.1.3
Summary: Curio-based web framework
Home-page: UNKNOWN
Author: UNKNOWN
Author-email: UNKNOWN
License: BSD
Keywords: Curio HTTP
Platform: UNKNOWN
